esi_utils_pager/__init__.py
esi_utils_pager/calc.py
esi_utils_pager/config.py
esi_utils_pager/configurator.py
esi_utils_pager/country.py
esi_utils_pager/econexposure.py
esi_utils_pager/emploss.py
esi_utils_pager/exposure.py
esi_utils_pager/growth.py
esi_utils_pager/pandas_container.py
esi_utils_pager/probs.py
esi_utils_pager/semimodel.py
esi_utils_pager/bin/config_pager.py
esi_utils_pager/bin/pagerlite.py
esi_utils_pager/data/API_NY.GDP.PCAP.CD_DS2_en_excel_v2.xls
esi_utils_pager/data/API_NY.GDP.PCAP.CD_DS2_en_excel_v2_4770383.xls
esi_utils_pager/data/WPP2015_POP_F02_POPULATION_GROWTH_RATE.xls
esi_utils_pager/data/countries.xlsx
esi_utils_pager/data/economic.xlsx
esi_utils_pager/data/economy.xml
esi_utils_pager/data/fatality.xlsx
esi_utils_pager/data/fatality.xml
esi_utils_pager/data/semi_casualty.hdf
esi_utils_pager/data/semi_casualty.xlsx
esi_utils_pager/data/semi_collapse_mmi.hdf
esi_utils_pager/data/semi_collapse_mmi.xlsx
esi_utils_pager/data/semi_inventory.hdf
esi_utils_pager/data/semi_inventory.xlsx
esi_utils_pager/data/semi_workforce.hdf
esi_utils_pager/data/semi_workforce.xlsx
esi_utils_pager-1.1.18.dist-info/licenses/LICENSE.md
esi_utils_pager-1.1.18.dist-info/METADATA
esi_utils_pager-1.1.18.dist-info/WHEEL
esi_utils_pager-1.1.18.dist-info/entry_points.txt
esi_utils_pager-1.1.18.dist-info/top_level.txt
esi_utils_pager-1.1.18.dist-info/RECORD
