Metadata-Version: 2.4
Name: esi-utils-pager
Version: 1.1.18
Summary: USGS PAGER loss modeling functionality
Author-email: Mike Hearne <mhearne@usgs.gov>
License: License
Keywords: losses,earthquake
Requires-Python: >=3.10
License-File: LICENSE.md
Requires-Dist: esi-utils-io
Requires-Dist: esi-utils-time
Requires-Dist: fiona
Requires-Dist: geopandas
Requires-Dist: h5py
Requires-Dist: mapio>=0.8.5
Requires-Dist: numpy>=1.26
Requires-Dist: openpyxl
Requires-Dist: pandas
Requires-Dist: ruamel.yaml
Requires-Dist: rasterio
Requires-Dist: scipy
Requires-Dist: shapely
Requires-Dist: xlrd
Provides-Extra: dev
Requires-Dist: build>=0.7.0; extra == "dev"
Requires-Dist: black>=21; extra == "dev"
Requires-Dist: flake8>=3.9; extra == "dev"
Requires-Dist: ipython>=7.26; extra == "dev"
Requires-Dist: notebook>=6.4.1; extra == "dev"
Requires-Dist: twine>=3.7.0; extra == "dev"
Provides-Extra: test
Requires-Dist: pytest>=6.2; extra == "test"
Requires-Dist: pytest-cov>=2.12.0; extra == "test"
Provides-Extra: build
Requires-Dist: build; extra == "build"
Requires-Dist: twine; extra == "build"
Requires-Dist: check-wheel-contents; extra == "build"
Dynamic: license-file
